bargeparse/__init__.py
bargeparse/actions.py
bargeparse/cli.py
bargeparse/command.py
bargeparse/conftest.py
bargeparse/test_bargeparse.py
bargeparse/test_positional_only_parameters.py
bargeparse-0.9.1.dist-info/LICENSE
bargeparse-0.9.1.dist-info/METADATA
bargeparse-0.9.1.dist-info/WHEEL
bargeparse-0.9.1.dist-info/top_level.txt
bargeparse-0.9.1.dist-info/RECORD
