Metadata-Version: 2.1
Name: bargeparse
Version: 0.9.1
Summary: Instrospect function signatures to construct a CLI
Home-page: https://github.com/shangxiao/bargeparse
Author: David Sanders
License: MIT
Platform: UNKNOWN
Requires-Python: >=3.6
